psbs/__init__.py
psbs/__main__.py
psbs/config.py
psbs/example.txt
psbs/extension.py
psbs/gister.py
psbs/htmlbuilder.py
psbs/project.py
psbs/psbs.py
psbs/psparser.py
psbs/template.py
psbs/token.py
psbs/utils.py
psbs/extensions/__init__.py
psbs/extensions/build.py
psbs/extensions/filters.py
psbs/extensions/images.py
psbs/extensions/tiled.py
psbs-0.3.3.dist-info/LICENSE
psbs-0.3.3.dist-info/METADATA
psbs-0.3.3.dist-info/WHEEL
psbs-0.3.3.dist-info/entry_points.txt
psbs-0.3.3.dist-info/top_level.txt
psbs-0.3.3.dist-info/RECORD
