Metadata-Version: 2.1
Name: psbs
Version: 0.3.3
Summary: PuzzleScript Build System
Home-page: https://github.com/jcmiller11/PSBS
Download-URL: https://github.com/jcmiller11/PSBS/archive/refs/tags/0.3.3.tar.gz
Author: J.C. Miller
Author-email: johncoreymiller@gmail.com
License: MIT
Classifier: Intended Audience :: Developers
Classifier: License :: OSI Approved :: MIT License
Classifier: Operating System :: OS Independent
Classifier: Programming Language :: Python :: 3
Classifier: Topic :: Games/Entertainment :: Puzzle Games
Classifier: Topic :: Software Development :: Build Tools
Requires-Python: >=3.8
License-File: LICENSE
Requires-Dist: jinja2
Requires-Dist: pyyaml
Requires-Dist: Pillow
Requires-Dist: platformdirs
Requires-Dist: requests
Requires-Dist: numpy
Requires-Dist: pyppeteer
